OHF/__init__.py
OHF/architecture.s.HTML
OHF/license.S.HTML
OHF/module.MD
OHF/module.s.HTML
OHF/__agenda/agenda.S.HTML
OHF/__agenda/maybes.s.HTML
OHF/__agenda/processes/errout/script.py
OHF/__agenda/processes/errout/start.py
OHF/__agenda/processes/errout_v1/script.py
OHF/__agenda/processes/errout_v1/start.py
OHF/__agenda/processes/errout_v2/script.py
OHF/__agenda/processes/errout_v2/start.py
OHF/_book/advanced tutorial.s.HTML
OHF/_book/book.s.HTML
OHF/_book/example output.s.HTML
OHF/_book/relevant.s.HTML
OHF/_clique/__init__.py
OHF/_clique/group/__init__.py
OHF/_status/establish.py
OHF/_status/status.proc.py
OHF/_status/status.s.HTML
OHF/_status/status_py.py
OHF/_status/DB/records.json
OHF/_status/monitors/-1_start/status_1.py
OHF/_status/monitors/-1_start/chassis/modules/monitor_1.py
OHF/_status/monitors/0_start/status_1.py
OHF/_status/monitors/0_start/chassis/modules/monitor_1.py
OHF/_status/monitors/1/status_1.py
OHF/_status/monitors/1/stasis/path_1_health.py
OHF/_status/monitors/1/stasis/path_2_health.py
OHF/_status/monitors/2/status_1.py
OHF/_status/monitors/2/stasis/1_health.py
OHF/_status/monitors/2/stasis/2_health.py
OHF/_status/monitors/2/stasis/modules/MODULE_1.py
OHF/_status/monitors/3_empty_glob/status_1.py
OHF/_status/monitors/4_bad_import/status_1.py
OHF/_status/monitors/4_bad_import/stasis/1_health.py
OHF/_status/monitors/5__file__/status_1.py
OHF/_status/monitors/5__file__/stasis/1_health.py
OHF/_status/monitors/5__file__/stasis/MODULES/MODULE_1.py
OHF/_status/monitors/6_various/status_1.py
OHF/_status/monitors/6_various/stasis/1_health.py
OHF/_status/monitors/6_various/stasis/2_health.py
OHF/_status/monitors/6_various/stasis/3_health.py
OHF/_status/monitors/6_various/stasis/MODULES/MODULE_1.py
OHF/_status/monitors/7/status_1.py
OHF/_status/monitors/7/stasis/guarantee_1.py
OHF/_status/monitors/8_DB/status_1.py
OHF/_status/monitors/8_DB/stasis/guarantee_1.py
OHF/_status/monitors/8_DB/variable/status_db/records.json
OHF/_status_advanced/status.proc.py
OHF-1.0.4.dist-info/METADATA
OHF-1.0.4.dist-info/WHEEL
OHF-1.0.4.dist-info/entry_points.txt
OHF-1.0.4.dist-info/top_level.txt
OHF-1.0.4.dist-info/RECORD
